quart_discord/__init__.py
quart_discord/_http.py
quart_discord/client.py
quart_discord/configs.py
quart_discord/exceptions.py
quart_discord/utils.py
quart_discord/models/__init__.py
quart_discord/models/base.py
quart_discord/models/connections.py
quart_discord/models/guild.py
quart_discord/models/integration.py
quart_discord/models/user.py
tests/__init__.py
tests/test_app.py
Quart_Discord_any-2.2.2b1.dist-info/LICENSE
Quart_Discord_any-2.2.2b1.dist-info/METADATA
Quart_Discord_any-2.2.2b1.dist-info/WHEEL
Quart_Discord_any-2.2.2b1.dist-info/top_level.txt
Quart_Discord_any-2.2.2b1.dist-info/RECORD
