Metadata-Version: 2.1
Name: Quart-Discord-any
Version: 2.2.2b1
Summary: Discord OAuth2 extension for Quart using modern Discord Libraries.
Home-page: https://github.com/Memotic/Quart-Discord-any
Author: Philip Dowie
Author-email: philip@jnawk.nz
Maintainer: William Hatcher
Maintainer-email: william@memotic.net
License: MIT
Platform: any
Classifier: Environment :: Web Environment
Classifier: Intended Audience :: Developers
Classifier: License :: OSI Approved :: MIT License
Classifier: Operating System :: OS Independent
Classifier: Programming Language :: Python :: 3
Classifier: Topic :: Internet :: WWW/HTTP :: Dynamic Content
Classifier: Topic :: Software Development :: Libraries :: Python Modules
Requires-Python: >=3.8
License-File: LICENSE
Requires-Dist: Quart
Requires-Dist: pyjwt
Requires-Dist: oauthlib
Requires-Dist: Async-OAuthlib
Requires-Dist: cachetools
Provides-Extra: discodpy
Requires-Dist: discord.py ; extra == 'discodpy'
Provides-Extra: docs
Requires-Dist: sphinx (==1.8.3) ; extra == 'docs'
Provides-Extra: nextcord
Requires-Dist: nextcord (==2.0.0) ; extra == 'nextcord'
Provides-Extra: pycord
Requires-Dist: py-cord ; extra == 'pycord'
